<!DOCTYPE transcription SYSTEM "http://www.livesandletters.ac.uk/schema/aor_20141023.dtd">

<transcription xmlns:xsi="http://www.w3.org/2001/XMLSchema-instance"
    xsi:noNamespaceSchemaLocation="https://raw.githubusercontent.com/ChrisRG/ReadingHamlet/master/RHschema.xsd">
    
    <page filename="Hamlet.004r.tif" pagination="7" signature="I.2" reader="John Ward"/> <!-- Signature = act + scene -->
    <annotation> 
        
        <!-- Substitutions -->
        
        <substitution method="pen" type="deletion" copyText="
            &quot; Than is the Throne of Denmark to thy Father: | 
            &quot; What would'st thou have Laertes?" amendedText=""/>
        
        <substitution method="pen" type="replacement" copyText="again toward France" amendedText="again for France"/>
        
        <substitution method="pen" type="deletion" copyText="&quot; And bow them to your gracious leave and pardon" amendedText=""/>
        
        <substitution method="pen" type="deletion" copyText="&quot; I do beseech you give him leave to go." amendedText=""/>        
        
        <substitution method="pen" type="deletion" copyText="And thy best graces; spend it at thy will." amendedText="spend it at thy will."/>
        
        <substitution method="pen" type="deletion" copyText="Ham. Not so much my Lord, I am too much in the Sun." amendedText="Ham. Not so my Lord, I am too much in the Sun."/>
        
        <substitution method="pen" type="replacement" copyText="'Tis not alone this mourning cloke could smother," amendedText="'Tis not alone this mourning suit good mother,"/>
        
        <substitution method="pen" type="deletion" copyText="
            &quot; Nor customary sutes of solemn black, | 
            &quot; Nor windy suspiration of forc'd breath, |
            &quot; No, nor the fruitful river in the eye, | 
            &quot; Nor the dejected haviour of the visage," amendedText=""/>
        
        <substitution method="pen" type="errata" copyText="moods," amendedText="moldes,"/>
        
        <substitution method="pen" type="replacement" copyText="&quot; For they are actions that a man might play:" amendedText=""/>
        
    </annotation>
</transcription>




